[
  {
    "id": "40286980-936a-430e-9ed9-7820409c5b5e",
    "author": "admin",
    "message": "admin",
    "image": null,
    "createdAt": "2024-03-29T00:05:10.211Z"
  },
  {
    "id": "61568a0f-9c1b-401b-a8a0-1bc4620ee617",
    "author": "Anonymous",
    "message": "new messages",
    "image": null,
    "createdAt": "2024-03-29T00:09:50.926Z"
  },
  {
    "id": "d1798336-4486-41f1-b3c8-234cc2454567",
    "author": "admin",
    "message": "message",
    "image": "images/e98bad07-1686-4dc9-99e4-b20cc1909ad1.png",
    "createdAt": "2024-03-29T00:10:40.646Z"
  },
  {
    "id": "59b4bae6-cee3-4707-98bc-81304e8022fb",
    "author": "sss",
    "message": "sss",
    "image": "images/d181b434-5875-4111-8523-56f4315c458d.png",
    "createdAt": "2024-03-29T00:11:14.474Z"
  }
]